xiyang_morph/__init__.py
xiyang_morph/config.py
xiyang_morph/face_detect_and_track.py
xiyang_morph/face_detection.py
xiyang_morph/face_points_detection.py
xiyang_morph/face_swap.py
xiyang_morph/morph.py
xiyang_morph/video_handler.py
xiyang_porch_pkg-1.0.1.dist-info/METADATA
xiyang_porch_pkg-1.0.1.dist-info/WHEEL
xiyang_porch_pkg-1.0.1.dist-info/top_level.txt
xiyang_porch_pkg-1.0.1.dist-info/RECORD
