Metadata-Version: 2.1
Name: xiyang-porch-pkg
Version: 1.0.1
Summary: morph package
Home-page: https://github.com/pypa/sampleproject
Author: Xiyang
Author-email: 838568501@qq.com
License: UNKNOWN
Platform: UNKNOWN
Classifier: Programming Language :: Python :: 3
Classifier: License :: OSI Approved :: MIT License
Classifier: Operating System :: OS Independent
